stormi/__init__.py
stormi/logging.py
stormi/main.py
stormi/plotting.py
stormi/posterior.py
stormi/train.py
stormi/evaluation/__init__.py
stormi/evaluation/metrics.py
stormi/evaluation/plotting.py
stormi/guides/AmortizedNormal.py
stormi/guides/AmortizedSplicing.py
stormi/guides/__init__.py
stormi/models/ATAC_RNA_v1.py
stormi/models/ATAC_RNA_v2.py
stormi/models/README.md
stormi/models/RNA_1layer.py
stormi/models/RNA_1layer_ManualEuler.py
stormi/models/RNA_1layer_constantDiffusion.py
stormi/models/RNA_1layer_constantDiffusion_LogNormal.py
stormi/models/RNA_1layer_simple.py
stormi/models/RNA_1layer_simple_constantDiffusion.py
stormi/models/RNA_2layers_ManualEuler.py
stormi/models/RNA_2layers_ManualEuler_MultiplePaths_Enumeration.py
stormi/models/RNA_2layers_ManualEuler_MultiplePaths_SoftWeights.py
stormi/models/RNA_2layers_MultiplePaths_SDE.py
stormi/models/RNA_2layers_MultiplePaths_SDE_v3.py
stormi/models/RNA_4layers_MultiplePaths_ODE.py
stormi/models/RNA_utils.py
stormi/models/__init__.py
stormi/models/_deterministic_inference.py
stormi/models/_deterministic_simulation.py
stormi/models/utils.py
stormi/plots/__init__.py
stormi/preprocessing/__init__.py
stormi/preprocessing/_complexity.py
stormi/preprocessing/_embedding.py
stormi/preprocessing/_file_utils.py
stormi/preprocessing/_filtering.py
stormi/preprocessing/_metacells.py
stormi/preprocessing/_motifs.py
stormi/preprocessing/_pipeline.py
stormi/preprocessing/_region_gene_tf.py
stormi/styles/__init__.py
stormi/styles/common.mplstyle
stormi/styles/configure.py
stormi/tests/.keep
stormi/tests/__init__.py
stormi/tests/conftest.py
stormi/tests/test_amortizedsplicing.py
stormi/tests/test_logging.py
stormi/tests/test_main.py
stormi/tests/test_preprocessing_rhg-to-rh.py
stormi/tests/test_workflow_1.py
stormi/tests/test_workflow_ATAC.py
stormi/tests/test_workflow_SDE.py
stormi/tests/models/__init__.py
stormi/tests/models/test_deterministic_inference.py
stormi/tests/models/test_deterministic_simulation.py
stormi-0.7.0.dist-info/METADATA
stormi-0.7.0.dist-info/WHEEL
stormi-0.7.0.dist-info/entry_points.txt
stormi-0.7.0.dist-info/RECORD
