Metadata-Version: 2.4
Name: stormi
Version: 0.7.0
Summary: Probabilistic modeling of cellular dynamics
Author-email: Cell Dynamics Team <celldynamics@proton.me>
Requires-Python: <3.13,>=3.11
Requires-Dist: arviz>=0.21.0
Requires-Dist: beartype>=0.20.0
Requires-Dist: diffrax>=0.6.1
Requires-Dist: einops>=0.8.1
Requires-Dist: funsor>=0.4.5
Requires-Dist: h5py>=3.13.0
Requires-Dist: igraph>=0.11.8
Requires-Dist: jax>=0.4.35; platform_system != 'Linux' or platform_machine != 'x86_64'
Requires-Dist: jax[cuda12]>=0.4.35; platform_system == 'Linux' and platform_machine == 'x86_64'
Requires-Dist: jaxtyping>=0.2.36
Requires-Dist: leidenalg>=0.10.2
Requires-Dist: matplotlib>=3.10.1
Requires-Dist: numpy>=2.1.3
Requires-Dist: numpyro>=0.18.0
Requires-Dist: optax>=0.2.4
Requires-Dist: pandas>=2.2.3
Requires-Dist: pythran>=0.16.1
Requires-Dist: rich>=13.9.4
Requires-Dist: scanpy>=1.11.0
Requires-Dist: scipy>=1.15.2
Requires-Dist: scvi-tools>=1.2.2
Requires-Dist: torch>=2.4.0
Requires-Dist: xarray>=2025.1.2
Provides-Extra: preprocessing
Requires-Dist: gtfparse; extra == 'preprocessing'
Requires-Dist: harmonypy>=0.0.10; extra == 'preprocessing'
Requires-Dist: pybiomart>=0.2.0; extra == 'preprocessing'
Requires-Dist: pyranges>=0.1.4; extra == 'preprocessing'
Requires-Dist: tangermeme>=0.4.0; extra == 'preprocessing'
